hentaihavenpy/__init__.py
hentaihavenpy/dababy.py
hentaihavenpy/fact.py
hentaihavenpy/nsfw.py
hentaihavenpy/rob.py
hentaihavenpy-0.2.dist-info/METADATA
hentaihavenpy-0.2.dist-info/WHEEL
hentaihavenpy-0.2.dist-info/top_level.txt
hentaihavenpy-0.2.dist-info/RECORD
