Metadata-Version: 2.1
Name: hentaihavenpy
Version: 0.2
Summary: haha hentai api go brrrrrrrrr cumshot in my ass
Home-page: https://hentaihaven.dev
Author: hentaihaven.edu
License: UNKNOWN
Platform: UNKNOWN
Requires-Dist: requests
